hoggorm/__init__.py
hoggorm/cross_val.py
hoggorm/mat_corr_coeff.py
hoggorm/pca.py
hoggorm/pcr.py
hoggorm/plsr1.py
hoggorm/plsr2.py
hoggorm/statTools.py
hoggorm/version.py
hoggorm-0.13.3.dist-info/LICENSE
hoggorm-0.13.3.dist-info/METADATA
hoggorm-0.13.3.dist-info/WHEEL
hoggorm-0.13.3.dist-info/top_level.txt
hoggorm-0.13.3.dist-info/RECORD
